odoo/addons/sale_product_company_multi_add/README.rst
odoo/addons/sale_product_company_multi_add/__init__.py
odoo/addons/sale_product_company_multi_add/__manifest__.py
odoo/addons/sale_product_company_multi_add/i18n/it.po
odoo/addons/sale_product_company_multi_add/i18n/sale_product_company_multi_add.pot
odoo/addons/sale_product_company_multi_add/readme/CONTRIBUTORS.rst
odoo/addons/sale_product_company_multi_add/readme/DESCRIPTION.rst
odoo/addons/sale_product_company_multi_add/static/description/icon.png
odoo/addons/sale_product_company_multi_add/static/description/index.html
odoo/addons/sale_product_company_multi_add/tests/__init__.py
odoo/addons/sale_product_company_multi_add/tests/test_sale_product_company_multi_add.py
odoo/addons/sale_product_company_multi_add/wizard/__init__.py
odoo/addons/sale_product_company_multi_add/wizard/sale_import_products.py
odoo/addons/sale_product_company_multi_add/wizard/sale_import_products_view.xml
odoo_addon_sale_product_company_multi_add-16.0.1.0.0.4.dist-info/METADATA
odoo_addon_sale_product_company_multi_add-16.0.1.0.0.4.dist-info/WHEEL
odoo_addon_sale_product_company_multi_add-16.0.1.0.0.4.dist-info/top_level.txt
odoo_addon_sale_product_company_multi_add-16.0.1.0.0.4.dist-info/RECORD
