Metadata-Version: 2.1
Name: odoo-addon-sale_product_company_multi_add
Version: 16.0.1.0.0.4
Summary: Filter products by selling companies on sale order multi add
Home-page: https://github.com/OCA/multi-company
Author: Camptocamp, Odoo Community Association (OCA)
Author-email: support@odoo-community.org
License: AGPL-3
Classifier: Programming Language :: Python
Classifier: Framework :: Odoo
Classifier: Framework :: Odoo :: 16.0
Classifier: License :: OSI Approved :: GNU Affero General Public License v3
Classifier: Development Status :: 3 - Alpha
Requires-Python: >=3.10
Requires-Dist: odoo-addon-sale-product-company<16.1dev,>=16.0dev
Requires-Dist: odoo-addon-sale-product-multi-add<16.1dev,>=16.0dev
Requires-Dist: odoo<16.1dev,>=16.0a
